colossalhq/__init__.py
colossalhq-0.0.1.dist-info/METADATA
colossalhq-0.0.1.dist-info/WHEEL
colossalhq-0.0.1.dist-info/RECORD
