Metadata-Version: 2.4
Name: colossalhq
Version: 0.0.1
Summary: ColossalHQ
Project-URL: Homepage, https://colossalhq.com
Author-email: ColossalHQ <admin@colossalhq.com>
License-Expression: MIT
Classifier: Development Status :: 4 - Beta
Classifier: License :: OSI Approved :: MIT License
Classifier: Programming Language :: Python :: 3
Requires-Python: >=3.8
